worker_x/__init__.py
worker_x-0.0.6.dist-info/METADATA
worker_x-0.0.6.dist-info/WHEEL
worker_x-0.0.6.dist-info/top_level.txt
worker_x-0.0.6.dist-info/RECORD
