Metadata-Version: 2.1
Name: worker-x
Version: 0.0.6
Summary: Multi threading worker
Author: Minhdz117
Keywords: worker,multi task,multi thread,threading
